phenoshift/__init__.py
phenoshift/main.py
phenoshift/errors/SeepParsingError.py
phenoshift/errors/SeepValidationError.py
phenoshift/errors/__init__.py
phenoshift/models/LoincId.py
phenoshift/models/LoincScale.py
phenoshift/models/Query.py
phenoshift/models/__init__.py
phenoshift/models/tests/__init__.py
phenoshift/models/tests/__init__.pyc
phenoshift/models/tests/test_loincId.py
phenoshift/models/tests/test_loincId.pyc
phenoshift/models/tests/test_loinc_scale.py
phenoshift/models/tests/test_loinc_scale.pyc
phenoshift/tests/__init__.py
phenoshift/tests/__init__.pyc
phenoshift/tests/test_annotation_file.tsv
phenoshift/tests/test_cli.py
phenoshift/tests/test_cli.pyc
phenoshift/tests/test_query.tsv
phenoshift/util/AnnotationParser.py
phenoshift/util/AnnotationResolver.py
phenoshift/util/AnnotationUtility.py
phenoshift/util/QueryFileParser.py
phenoshift/util/__init__.py
phenoshift/util/tests/__init__.py
phenoshift/util/tests/__init__.pyc
phenoshift/util/tests/test_annotation_file.tsv
phenoshift/util/tests/test_annotation_parser.py
phenoshift/util/tests/test_annotation_parser.pyc
phenoshift/util/tests/test_annotation_resolver.py
phenoshift/util/tests/test_annotation_resolver.pyc
phenoshift/util/tests/test_annotation_utility.py
phenoshift/util/tests/test_annotation_utility.pyc
phenoshift/util/tests/test_query.tsv
phenoshift/util/tests/test_query_parser.py
phenoshift/util/tests/test_query_parser.pyc
phenoshift-1.0.0.data/data/LICENSE.txt
phenoshift-1.0.0.data/data/requirements.txt
phenoshift-1.0.0.dist-info/LICENSE.txt
phenoshift-1.0.0.dist-info/METADATA
phenoshift-1.0.0.dist-info/WHEEL
phenoshift-1.0.0.dist-info/entry_points.txt
phenoshift-1.0.0.dist-info/top_level.txt
phenoshift-1.0.0.dist-info/RECORD
