Metadata-Version: 2.1
Name: phenoshift
Version: 1.0.0
Summary: Python version of LOINC2HPO
Home-page: https://github.com/TheJacksonLaboratory/phenoshift
Author: Michael Gargano
Author-email: michael.gargano@jax.com
License: GPLv3
Keywords: python,loinc to hpo
Platform: UNKNOWN
Requires-Dist: click (==7.1.2)
Requires-Dist: ddt (==1.4.1)
